nextbox/__init__.py
nextbox/conf.py
nextbox/func.py
nextbox/module/__init__.py
nextbox/module/camera.py
nextbox/module/los.py
nextbox/node.py
nextbox-0.1.15.dist-info/WHEEL
nextbox-0.1.15.dist-info/METADATA
nextbox-0.1.15.dist-info/RECORD
