Metadata-Version: 2.1
Name: nextbox
Version: 0.1.15
Summary: 
Author: lijianan
Author-email: lijianan@tezign.com
Requires-Python: >=3.8,<4.0
Classifier: Programming Language :: Python :: 3
Classifier: Programming Language :: Python :: 3.10
Classifier: Programming Language :: Python :: 3.8
Classifier: Programming Language :: Python :: 3.9
Requires-Dist: PyYAML (>=6.0,<7.0)
Requires-Dist: loguru (>=0.6.0,<0.7.0)
Requires-Dist: nats-py (>=2.2.0,<3.0.0)
Requires-Dist: pydantic (>=1.10.2,<2.0.0)
